morseg/__init__.py
morseg/algorithms/__init__.py
morseg/algorithms/similarity.py
morseg/algorithms/tokenizer.py
morseg/datastruct/__init__.py
morseg/datastruct/trie.py
morseg/utils/__init__.py
morseg/utils/wrappers.py
morseg-0.1.dist-info/METADATA
morseg-0.1.dist-info/WHEEL
morseg-0.1.dist-info/top_level.txt
morseg-0.1.dist-info/RECORD
