Metadata-Version: 2.1
Name: morseg
Version: 0.1
Summary: Morpheme Segmentation in Multi- and Monolingual Wordlists
Author-email: Arne Rubehn <arne.rubehn@uni-passau.de>, Johann-Mattis List <mattis.list@uni-passau.de>
Maintainer-email: Arne Rubehn <arne.rubehn@uni-passau.de>, Johann-Mattis List <mattis.list@uni-passau.de>
License: MIT
Project-URL: Homepage, https://github.com/calc-project/morseg/
Keywords: linguistics,morpheme segmentation,computational linguistics
Classifier: Development Status :: 5 - Production/Stable
Classifier: Intended Audience :: Developers
Classifier: Intended Audience :: Science/Research
Classifier: Natural Language :: English
Classifier: Operating System :: OS Independent
Classifier: Programming Language :: Python :: 3
Classifier: Programming Language :: Python :: 3.8
Classifier: Programming Language :: Python :: 3.9
Classifier: Programming Language :: Python :: 3.10
Classifier: Programming Language :: Python :: 3.11
Classifier: Programming Language :: Python :: 3.12
Classifier: Programming Language :: Python :: Implementation :: CPython
Classifier: Programming Language :: Python :: Implementation :: PyPy
Classifier: License :: OSI Approved :: GNU General Public License v3 (GPLv3)
Requires-Python: >=3.8
Requires-Dist: numpy
Requires-Dist: linse
Requires-Dist: morfessor
Requires-Dist: tqdm
Provides-Extra: dev
Requires-Dist: build ; extra == 'dev'
Requires-Dist: wheel ; extra == 'dev'
Requires-Dist: twine ; extra == 'dev'
Requires-Dist: sphinx ; extra == 'dev'
Requires-Dist: tox ; extra == 'dev'
Requires-Dist: black ; extra == 'dev'
Provides-Extra: test
Requires-Dist: pytest ; extra == 'test'
Requires-Dist: coverage ; extra == 'test'
Requires-Dist: pytest-mock ; extra == 'test'
Requires-Dist: pytest-cov ; extra == 'test'
